{
  "slug": "onenote.get_current_user",
  "service": "onenote.cloud.microsoft",
  "intentSynonyms": [
    "get a current user in onenote",
    "look up a current user in onenote",
    "fetch a single current user in onenote",
    "view one specific current user in onenote",
    "get current user in onenote",
    "get the current user profile in onenote"
  ],
  "description": "Get the profile of the currently authenticated Microsoft user including name, email, and language preference.",
  "actionVerb": "get",
  "sideEffectClass": "read",
  "params": {
    "type": "object",
    "properties": {},
    "additionalProperties": false
  },
  "backing": "handler",
  "provenance": {
    "source": "opentabs",
    "sha": "4b17021637d2cac12b8d84d21c40e765aa7b85e9",
    "sourcePath": "plugins/onenote/src/tools/get-current-user.ts",
    "license": "MIT",
    "signals": {
      "transportHelper": "api",
      "httpMethod": "GET",
      "opNameVerb": "get"
    }
  }
}
