{
  "slug": "cloudflare.get_zone_settings",
  "service": "dash.cloudflare.com",
  "intentSynonyms": [
    "get zone settings in cloudflare",
    "look up zone settings in cloudflare",
    "fetch a single zone settings in cloudflare",
    "view one specific zone settings in cloudflare",
    "get all zone settings in cloudflare"
  ],
  "description": "Get all settings for a zone. Returns ~56 settings including security level, SSL mode, cache TTL, minification, HTTP/2, Always Use HTTPS, Brotli compression, development mode, and more. Each setting shows its current value and whether it is editable on the current plan.",
  "actionVerb": "get",
  "sideEffectClass": "read",
  "params": {
    "type": "object",
    "properties": {
      "zone_id": {
        "type": "string",
        "description": "Zone ID (32-char hex string)"
      }
    },
    "required": [
      "zone_id"
    ],
    "additionalProperties": false
  },
  "backing": "dom",
  "provenance": {
    "source": "opentabs",
    "sha": "4b17021637d2cac12b8d84d21c40e765aa7b85e9",
    "sourcePath": "plugins/cloudflare/src/tools/get-zone-settings.ts",
    "license": "MIT",
    "signals": {
      "transportHelper": null,
      "httpMethod": null,
      "opNameVerb": "get"
    }
  }
}
