{
  "slug": "dominos.list_stores",
  "service": "www.dominos.com",
  "intentSynonyms": [
    "list stores in dominos",
    "show me my stores in dominos",
    "view my stores in dominos",
    "see all my stores in dominos",
    "find nearby dominos stores in dominos"
  ],
  "description": "List nearby Domino’s stores by address or ZIP code, with their hours and delivery/carryout availability.",
  "actionVerb": "list",
  "sideEffectClass": "read",
  "params": {
    "type": "object",
    "properties": {
      "address": {
        "type": "string",
        "minLength": 1,
        "description": "Address or ZIP code to search near"
      },
      "service": {
        "description": "Filter by service type",
        "type": "string",
        "enum": [
          "delivery",
          "carryout"
        ]
      }
    },
    "required": [
      "address"
    ],
    "additionalProperties": false
  },
  "backing": "dom",
  "provenance": {
    "source": "opentabs",
    "sha": "4b17021637d2cac12b8d84d21c40e765aa7b85e9",
    "sourcePath": "plugins/dominos/src/tools/list-stores.ts",
    "license": "MIT",
    "signals": {
      "transportHelper": "api",
      "httpMethod": "GET",
      "opNameVerb": "list"
    }
  }
}
